[
    {
        "id": "01",
        "label": "Alabama",
        "value": 15.6
    },
    {
        "id": "02",
        "label": "Alaska",
        "value": 10.2
    },
    {
        "id": "04",
        "label": "Arizona",
        "value": 12.8
    },
    {
        "id": "05",
        "label": "Arkansas",
        "value": 16.0
    },
    {
        "id": "06",
        "label": "California",
        "value": 12.0
    },
    {
        "id": "08",
        "label": "Colorado",
        "value": 9.4
    },
    {
        "id": "09",
        "label": "Connecticut",
        "value": 10.0
    },
    {
        "id": "10",
        "label": "Delaware",
        "value": 10.7
    },
    {
        "id": "11",
        "label": "District of Columbia",
        "value": 14.5
    },
    {
        "id": "12",
        "label": "Florida",
        "value": 12.6
    },
    {
        "id": "13",
        "label": "Georgia",
        "value": 13.5
    },
    {
        "id": "15",
        "label": "Hawaii",
        "value": 10.0
    },
    {
        "id": "16",
        "label": "Idaho",
        "value": 10.6
    },
    {
        "id": "17",
        "label": "Illinois",
        "value": 11.7
    },
    {
        "id": "18",
        "label": "Indiana",
        "value": 12.2
    },
    {
        "id": "19",
        "label": "Iowa",
        "value": 11.0
    },
    {
        "id": "20",
        "label": "Kansas",
        "value": 11.5
    },
    {
        "id": "21",
        "label": "Kentucky",
        "value": 16.1
    },
    {
        "id": "22",
        "label": "Louisiana",
        "value": 18.9
    },
    {
        "id": "23",
        "label": "Maine",
        "value": 10.8
    },
    {
        "id": "24",
        "label": "Maryland",
        "value": 9.3
    },
    {
        "id": "25",
        "label": "Massachusetts",
        "value": 10.0
    },
    {
        "id": "26",
        "label": "Michigan",
        "value": 13.1
    },
    {
        "id": "27",
        "label": "Minnesota",
        "value": 9.2
    },
    {
        "id": "28",
        "label": "Mississippi",
        "value": 19.1
    },
    {
        "id": "29",
        "label": "Missouri",
        "value": 12.6
    },
    {
        "id": "30",
        "label": "Montana",
        "value": 12.0
    },
    {
        "id": "31",
        "label": "Nebraska",
        "value": 10.3
    },
    {
        "id": "32",
        "label": "Nevada",
        "value": 12.6
    },
    {
        "id": "33",
        "label": "New Hampshire",
        "value": 7.2
    },
    {
        "id": "34",
        "label": "New Jersey",
        "value": 9.8
    },
    {
        "id": "35",
        "label": "New Mexico",
        "value": 18.1
    },
    {
        "id": "36",
        "label": "New York",
        "value": 13.7
    },
    {
        "id": "37",
        "label": "North Carolina",
        "value": 13.2
    },
    {
        "id": "38",
        "label": "North Dakota",
        "value": 10.6
    },
    {
        "id": "39",
        "label": "Ohio",
        "value": 13.2
    },
    {
        "id": "40",
        "label": "Oklahoma",
        "value": 15.3
    },
    {
        "id": "41",
        "label": "Oregon",
        "value": 11.9
    },
    {
        "id": "42",
        "label": "Pennsylvania",
        "value": 11.8
    },
    {
        "id": "44",
        "label": "Rhode Island",
        "value": 10.9
    },
    {
        "id": "45",
        "label": "South Carolina",
        "value": 14.2
    },
    {
        "id": "46",
        "label": "South Dakota",
        "value": 12.0
    },
    {
        "id": "47",
        "label": "Tennessee",
        "value": 13.8
    },
    {
        "id": "48",
        "label": "Texas",
        "value": 13.8
    },
    {
        "id": "49",
        "label": "Utah",
        "value": 8.6
    },
    {
        "id": "50",
        "label": "Vermont",
        "value": 10.3
    },
    {
        "id": "51",
        "label": "Virginia",
        "value": 9.9
    },
    {
        "id": "53",
        "label": "Washington",
        "value": 9.9
    },
    {
        "id": "54",
        "label": "West Virginia",
        "value": 16.6
    },
    {
        "id": "55",
        "label": "Wisconsin",
        "value": 10.6
    },
    {
        "id": "56",
        "label": "Wyoming",
        "value": 10.7
    },
    {
        "id": "72",
        "label": "Puerto Rico",
        "value": 41.6
    }
]